norfairwhl/__init__.py
norfairwhl/camera_motion.py
norfairwhl/distances.py
norfairwhl/drawing/__init__.py
norfairwhl/drawing/absolute_grid.py
norfairwhl/drawing/color.py
norfairwhl/drawing/draw_boxes.py
norfairwhl/drawing/draw_points.py
norfairwhl/drawing/drawer.py
norfairwhl/drawing/fixed_camera.py
norfairwhl/drawing/path.py
norfairwhl/drawing/utils.py
norfairwhl/filter.py
norfairwhl/metrics.py
norfairwhl/py.typed
norfairwhl/tracker.py
norfairwhl/utils.py
norfairwhl/video.py
norfairwhl-2.2.0.dist-info/LICENSE
norfairwhl-2.2.0.dist-info/METADATA
norfairwhl-2.2.0.dist-info/WHEEL
norfairwhl-2.2.0.dist-info/RECORD
