Metadata-Version: 2.1
Name: norfairwhl
Version: 2.2.0
Summary: Lightweight Python library for adding real-time multi-object tracking to any detector.
Home-page: https://github.com/tryolabs/norfair
License: BSD-3-Clause
Keywords: tracking,object-detection,object-tracking,kalman-filter,pose-estimation,re-identification,multi-object-tracking,re-id,tracking-algorithm,deepsort,video-tracking,video-inference-loop
Author: Tryolabs
Author-email: hello@tryolabs.com
Requires-Python: >=3.8,<4.0
Classifier: Development Status :: 5 - Production/Stable
Classifier: Intended Audience :: Developers
Classifier: Intended Audience :: Science/Research
Classifier: License :: OSI Approved :: BSD License
Classifier: Operating System :: OS Independent
Classifier: Programming Language :: Python :: 3
Classifier: Programming Language :: Python :: 3.8
Classifier: Programming Language :: Python :: 3.9
Classifier: Programming Language :: Python :: 3.10
Classifier: Programming Language :: Python :: 3.11
Classifier: Programming Language :: Python :: 3.12
Classifier: Topic :: Multimedia :: Video
Classifier: Topic :: Scientific/Engineering
Classifier: Topic :: Scientific/Engineering :: Artificial Intelligence
Classifier: Topic :: Scientific/Engineering :: Image Recognition
Classifier: Topic :: Software Development :: Libraries
Classifier: Topic :: Software Development :: Libraries :: Python Modules
Provides-Extra: metrics
Provides-Extra: video
Requires-Dist: filterpywhl (>=1.4.5,<2.0.0)
Requires-Dist: importlib-metadata (==4.8.3) ; python_version < "3.8"
Requires-Dist: motmetrics (==1.4.0) ; extra == "metrics"
Requires-Dist: numpy (>=1.19.0,<2.0.0) ; python_version < "3.8"
Requires-Dist: numpy (>=1.23.0,<2.0.0) ; python_version >= "3.8"
Requires-Dist: opencv-python (>=3.2.0,<5.0.0) ; extra == "video"
Requires-Dist: rich (>=9.10.0,<13.0.0)
Requires-Dist: scipy (>=1.5.4)
Project-URL: Repository, https://github.com/tryolabs/norfair
